scientific_tools/__init__.py
scientific_tools/graphics/__init__.py
scientific_tools/graphics/function_graphs.py
scientific_tools/graphics/spectral_analysis_graphs.py
scientific_tools/graphics/uncertainty_graphs.py
scientific_tools/mathematics/solve.py
scientific_tools/physics/__init__.py
scientific_tools/physics/spectral_analysis.py
scientific_tools/physics/uncertainty.py
scientific_tools-0.0.0a27.dist-info/LICENSE
scientific_tools-0.0.0a27.dist-info/METADATA
scientific_tools-0.0.0a27.dist-info/WHEEL
scientific_tools-0.0.0a27.dist-info/top_level.txt
scientific_tools-0.0.0a27.dist-info/RECORD
