Metadata-Version: 2.1
Name: scientific-tools
Version: 0.0.0a27
Summary: Scientific tools is the Swiss army knife of scientists, researchers, engineers and students who work with python.
Author-email: Cyprien BONTRON <c.b.e.python@gmail.com>
Maintainer-email: Cyprien BONTRON <c.b.e.python@gmail.com>
License: Creative Commons Attribution-NonCommercial-ShareAlike 4.0 International Public License
Project-URL: Download-URL, https://pypi.org/project/scientific_tools/
Classifier: Programming Language :: Python :: 3.7
Classifier: Programming Language :: Python :: 3.8
Classifier: Programming Language :: Python :: 3.9
Classifier: Programming Language :: Python :: 3.10
Classifier: Programming Language :: Python :: 3.11
Classifier: Natural Language :: English
Classifier: Intended Audience :: Science/Research
Classifier: Intended Audience :: Education
Classifier: License :: Free for non-commercial use
Classifier: Development Status :: 2 - Pre-Alpha
Requires-Python: >=3.7
License-File: LICENSE
Requires-Dist: numpy
Requires-Dist: matplotlib
